enhterm/__init__.py
enhterm/__version__.py
enhterm/base.py
enhterm/constants.py
enhterm/errors.py
enhterm/runner.py
enhterm/term.py
enhterm/variables.py
enhterm/command/__init__.py
enhterm/command/error.py
enhterm/command/noop.py
enhterm/command/quit.py
enhterm/command/text.py
enhterm/command/unknown.py
enhterm/impl/__init__.py
enhterm/impl/p2p/__init__.py
enhterm/impl/p2p/p2p_concern.py
enhterm/impl/p2p/p2p_provider.py
enhterm/impl/p2p/p2p_runner.py
enhterm/impl/p2p/p2p_watcher.py
enhterm/message/__init__.py
enhterm/mixins/__init__.py
enhterm/mixins/queued.py
enhterm/mixins/serializable.py
enhterm/mixins/stream.py
enhterm/prescriptions/__init__.py
enhterm/prescriptions/argument.py
enhterm/prescriptions/context.py
enhterm/prescriptions/errors.py
enhterm/prescriptions/mixins.py
enhterm/prescriptions/prescription.py
enhterm/provider/__init__.py
enhterm/provider/parser_provider.py
enhterm/provider/queue_provider.py
enhterm/provider/stream_provider.py
enhterm/provider/text_provider.py
enhterm/provider/parser/__init__.py
enhterm/provider/parser/argparser/__init__.py
enhterm/provider/parser/argparser/commands.py
enhterm/ser_deser/__init__.py
enhterm/ser_deser/dsds.py
enhterm/util/__init__.py
enhterm/util/validators.py
enhterm/watcher/__init__.py
enhterm/watcher/echo.py
enhterm-0.2.1.dist-info/LICENSE
enhterm-0.2.1.dist-info/METADATA
enhterm-0.2.1.dist-info/WHEEL
enhterm-0.2.1.dist-info/top_level.txt
enhterm-0.2.1.dist-info/RECORD
