Metadata-Version: 2.1
Name: enhterm
Version: 0.2.1
Summary: A Cmd-based framework for writing line-oriented command interpreters.
Home-page: https://github.com/pyl1b/enhterm
Author: Nicu Tofan
Author-email: nicu.tofan@gmail.com
License: MIT
Download-URL: https://github.com/pyl1b/enhterm/archive/v0.2.1.zip
Project-URL: Bug Tracker, https://github.com/pyl1b/enhterm/issues
Project-URL: Documentation, https://readthedocs.org/projects/enhterm/
Project-URL: Source Code, https://github.com/pyl1b/enhterm
Platform: UNKNOWN
Classifier: Development Status :: 3 - Alpha
Classifier: Intended Audience :: Developers
Classifier: Environment :: Console
Classifier: License :: OSI Approved :: MIT License
Classifier: Programming Language :: Python
Classifier: Programming Language :: Python :: 3
Classifier: Programming Language :: Python :: 3.6
Classifier: Programming Language :: Python :: Implementation :: CPython
Classifier: Programming Language :: Python :: Implementation :: PyPy
Requires-Python: >=3.6.0
Requires-Dist: u-msgpack-python
Provides-Extra: dev
Requires-Dist: nose ; extra == 'dev'
Requires-Dist: twine ; extra == 'dev'
Requires-Dist: wheel ; extra == 'dev'
Requires-Dist: sphinx ; extra == 'dev'
Requires-Dist: sphinx-rtd-theme ; extra == 'dev'
Requires-Dist: recommonmark ; extra == 'dev'
Requires-Dist: m2r ; extra == 'dev'
Requires-Dist: coverage ; extra == 'dev'
Requires-Dist: argparse ; extra == 'dev'
Requires-Dist: appupup ; extra == 'dev'
Requires-Dist: p2p0mq ; extra == 'dev'
Provides-Extra: full
Requires-Dist: argparse ; extra == 'full'
Provides-Extra: tests
Requires-Dist: mock ; extra == 'tests'
Requires-Dist: nose ; extra == 'tests'
Requires-Dist: argparse ; extra == 'tests'
Requires-Dist: appupup ; extra == 'tests'
Requires-Dist: p2p0mq ; extra == 'tests'
